{"weeks":[{"wk":"2026-W16","date":"2026-04-19","d":{"AXTI":1,"LITE":2,"HYMC":3,"AAOI":4,"BE":5,"AEHR":6,"PL":7,"CIEN":8,"CAR":9,"LASR":10,"FSLY":11,"COHR":12,"FORM":13,"MU":14,"AMPX":15,"APLD":16,"NBIS":17,"CIFR":18,"SATS":19,"IREN":20,"HUT":21,"POWL":22,"FIX":23,"AGX":24,"GLW":25,"NVTS":26,"AMKR":27,"AEIS":28,"MKSI":29,"CENX":30,"GSAT":31,"CLS":32,"DOCN":33,"INTC":34,"PARR":35,"LRCX":36,"MOD":37,"LGN":38,"LUNR":39,"ALB":40,"FN":41,"ONTO":42,"MTZ":43,"HBM":44,"ATI":45,"IRDM":46,"FTI":47,"KEYS":48,"MRVL":49,"GEV":50,"ECG":51,"FIVE":52,"FRO":53,"LSCC":54,"MTSI":55,"NOK":56,"MPWR":57,"CRDO":58,"AMAT":59,"BTSG":60,"MYRG":61,"AA":62,"AU":63,"CAT":64,"CRS":65,"KLAC":66,"DELL":67,"MT":68,"MRNA":69,"IESC":70,"LFUS":71,"NVT":72,"AMD":73,"ON":74,"ACLS":75,"ESE":76,"DAVE":77,"CGNX":78,"JBL":79,"ACHC":80,"ESI":81,"FLEX":82,"FDX":83,"ENTG":84,"FCX":85,"ALAB":86,"CMI":87,"ADI":88,"PLUG":89,"DBD":90,"CRUS":91,"JBHT":92,"CORZ":93,"ARW":94,"ANET":95,"AVT":96,"GFS":97,"EQX":98,"ASML":99,"C":100,"ONDS":101,"DHT":102,"KGC":103,"CCJ":104,"PLXS":105,"AVGO":106,"PAAS":107,"LUMN":108,"MRX":109,"EQIX":110,"NUE":111,"DNN":112,"DY":113,"GOOGL":114,"AGI":115,"CW":116,"CRWV":117,"APH":118,"DAR":119,"GOOG":120,"BWXT":121,"ATMU":122,"MSGS":123,"MAR":124,"ODFL":125,"ARM":126,"KNX":127,"ITT":128,"FTAI":129,"FLS":130,"FCFS":131,"EME":132,"HWM":133,"HTZ":134,"PR":135,"LMND":136,"IBKR":137,"HST":138,"AG":139,"GFI":140,"NEM":141,"AEM":142,"DD":143,"JCI":144,"NPO":145,"APG":146,"PVH":147,"BK":148,"IAG":149,"MEOH":150,"HAL":151,"CHRW":152,"GNRC":153,"CASY":154,"NTRS":155,"CDE":156,"BWA":157,"ALSN":158,"HL":159,"IDCC":160,"FNV":161,"KEX":162,"HLT":163,"IRM":164,"CE":165,"HAS":166,"BPOP":167,"CFG":168,"HPE":169,"DLR":170,"EBAY":171,"PLD":172,"BP":173,"MUR":174,"HXL":175,"GMED":176,"AAP":177,"MCHP":178,"RELY":179,"CAVA":180,"DOW":181,"JBLU":182,"AZN":183,"ETR":184,"CSX":185,"ASTS":186,"MRK":187,"CSCO":188,"MS":189,"COKE":190,"PH":191,"CLH":192,"GRMN":193,"BURL":194,"AME":195,"EVR":196,"NVDA":197,"B":198,"GM":199,"GLNG":200,"HUBB":201,"PCAR":202,"GKOS":203,"BNL":204,"ILMN":205,"EXPE":206,"FUTU":207,"FLY":208,"IONS":209,"BKR":210,"IBP":211,"DAL":212,"CROX":213,"EXK":214,"BEN":215,"GS":216,"CBOE":217,"ARMK":218,"BALL":219,"NDSN":220,"ETN":221,"BKH":222,"FRT":223,"KIM":224,"NOV":225,"AEO":226,"KEY":227,"CTRE":228,"MDLN":229,"RIVN":230,"GH":231,"M":232,"AMG":233,"MLI":234,"JLL":235,"AEP":236,"FERG":237,"APA":238,"EIX":239,"CAH":240,"ARGX":241,"ALLY":242,"BMY":243,"NRG":244,"DOV":245,"H":246,"LBRT":247,"AHR":248,"EWBC":249,"FTV":250,"NI":251,"HII":252,"GAP":253,"LVS":254,"CTVA":255,"NET":256,"OHI":257,"PFG":258,"NLY":259,"AMZN":260,"PNC":261,"MEDP":262,"LUV":263,"NEE":264,"GWW":265,"MTCH":266,"PBF":267,"LHX":268,"DE":269,"FITB":270,"FNB":271,"PFE":272,"ASO":273,"PNW":274,"MGM":275,"CRGY":276,"IVZ":277,"ALGN":278,"EVRG":279,"COLB":280,"ALHC":281,"IEX":282,"LNT":283,"AIT":284,"AEE":285,"DINO":286,"MP":287,"CVNA":288,"MUSA":289,"NYT":290,"AGNC":291,"MTB":292,"CB":293,"O":294,"CFR":295,"ALL":296,"NXT":297,"OVV":298,"CHRD":299,"LCII":300,"FHN":301,"NSC":302,"LOGI":303,"AAPL":304,"BAC":305,"HSIC":306,"HIG":307,"PPL":308,"CRSP":309,"GILD":310,"AMGN":311,"FE":312,"ATO":313,"CNP":314,"APD":315,"DVN":316,"BG":317,"CF":318,"MTDR":319,"HON":320,"EPRT":321,"CINF":322,"ADC":323,"ABNB":324,"FLR":325,"ORA":326,"OKLO":327,"AGCO":328,"DKS":329,"MPC":330,"OSK":331,"LEU":332,"AS":333,"CRL":334,"JPM":335,"FFIV":336,"PSA":337,"OXY":338,"LYB":339,"FANG":340,"HCA":341,"LECO":342,"GE":343,"EXPD":344,"DX":345,"CCL":346,"EMR":347,"IONQ":348,"EG":349,"COP":350,"NTRA":351,"LIN":352,"DTE":353,"IFF":354,"CTRA":355,"MNST":356,"BIDU":357,"CPA":358,"BMNR":359,"DECK":360,"ONB":361,"CACC":362,"ETSY":363,"F":364,"APP":365,"CMS":366,"FOXA":367,"ACGL":368,"CZR":369,"CHH":370,"JNJ":371,"CVX":372,"PII":373,"OMF":374,"ITW":375,"CRCL":376,"AFL":377,"GLPI":378,"HOG":379,"DTM":380,"CRH":381,"CCK":382,"LYV":383,"AAON":384,"KRMN":385,"EPD":386,"PCG":387,"PEP":388,"RS":389,"EMN":390,"META":391,"PPG":392,"CR":393,"CPAY":394,"EOG":395,"MO":396,"PHM":397,"ANF":398,"CVS":399,"COST":400,"NTR":401,"ADM":402,"KO":403,"GME":404,"BIO":405,"BIIB":406,"INSM":407,"DVA":408,"DG":409,"D":410,"ELS":411,"AN":412,"OMC":413,"KMI":414,"LNG":415,"ET":416,"FRPT":417,"NU":418,"CUBE":419,"JD":420,"MSI":421,"PSTG":422,"QRVO":423,"HOOD":424,"CARR":425,"MET":426,"OKE":427,"ES":428,"BA":429,"AFRM":430,"MC":431,"DOC":432,"OSCR":433,"AUR":434,"LH":435,"HBAN":436,"FCNCA":437,"EXR":438,"AKAM":439,"LMT":440,"CNX":441,"HESM":442,"DHI":443,"AXP":444,"LAZ":445,"EAT":446,"FAST":447,"MLM":448,"IR":449,"MTD":450,"AIG":451,"CART":452,"AR":453,"BOOT":454,"CHD":455,"PB":456,"NTAP":457,"CLSK":458,"NOC":459,"MPLX":460,"EQT":461,"GGG":462,"CBRE":463,"CDNS":464,"MCK":465,"LLY":466,"LOW":467,"EQR":468,"CSL":469,"PFGC":470,"MAS":471,"MSCI":472,"CVCO":473,"BTDR":474,"DUK":475,"ED":476,"PKG":477,"BDX":478,"ECL":479,"CMCSA":480,"NDAQ":481,"FWONK":482,"DGX":483,"CME":484,"DDOG":485,"MCD":486,"PEG":487,"EHC":488,"ESS":489,"EXC":490,"IDXX":491,"BLD":492,"NXPI":493,"HMY":494,"CCI":495,"COR":496,"MKL":497,"BABA":498,"NWSA":499,"CI":500,"NXST":501,"MIDD":502,"AAL":503,"DIS":504,"PNFP":505,"ORLY":506,"INVH":507,"PSKY":508,"ABBV":509,"DRI":510,"BLK":511,"PDD":512,"NFLX":513,"AMT":514,"MDB":515,"MMM":516,"HQY":517,"CDW":518,"BBY":519,"COF":520,"PLTR":521,"CG":522,"KVUE":523,"OC":524,"BKNG":525,"CHTR":526,"BTU":527,"GEHC":528,"AYI":529,"CPT":530,"A":531,"MTN":532,"LYFT":533,"EW":534,"KR":535,"NCLH":536,"CEG":537,"ICE":538,"MA":539,"FTNT":540,"GD":541,"FROG":542,"PG":543,"CRWD":544,"ORCL":545,"KTOS":546,"CL":547,"AVY":548,"AZO":549,"NEU":550,"AVB":551,"BAM":552,"AON":553,"IQV":554,"CNR":555,"AMCR":556,"NTES":557,"AMH":558,"FIGR":559,"CPNG":560,"JHX":561,"GLXY":562,"HD":563,"MARA":564,"FNF":565,"MAA":566,"IBM":567,"PEGA":568,"BIRK":569,"HPQ":570,"DLTR":571,"AWK":572,"ALNY":573,"MHK":574,"MSFT":575,"MCO":576,"ALK":577,"CLF":578,"J":579,"COMP":580,"CHDN":581,"BROS":582,"BRZE":583,"HSY":584,"FSLR":585,"CNH":586,"MDLZ":587,"ISRG":588,"NVR":589,"LAD":590,"PANW":591,"HEI":592,"CNC":593,"GPN":594,"LW":595,"APO":596,"LPLA":597,"PYPL":598,"ALLE":599,"DHR":600,"PGR":601,"AMP":602,"ELV":603,"HLI":604,"BX":605,"COIN":606,"AOS":607,"GPC":608,"QCOM":609,"KRC":610,"MRSH":611,"KKR":612,"HUM":613,"CACI":614,"PM":615,"MDT":616,"PNR":617,"ESAB":618,"LII":619,"BXP":620,"JEF":621,"IOT":622,"BAH":623,"BRK-B":624,"ADSK":625,"EQH":626,"MELI":627,"EFX":628,"KDP":629,"CTAS":630,"DBX":631,"CNM":632,"KMB":633,"DASH":634,"INFY":635,"CHWY":636,"MSTR":637,"BJ":638,"EXP":639,"AJG":640,"MORN":641,"EXE":642,"COO":643,"ACI":644,"OTIS":645,"DPZ":646,"IP":647,"CMG":648,"BAX":649,"EXLS":650,"LDOS":651,"POOL":652,"QUBT":653,"CVLT":654,"DXCM":655,"KHC":656,"BILL":657,"ACM":658,"EOSE":659,"CLX":660,"KNSL":661,"ONON":662,"LEN":663,"PCOR":664,"BSY":665,"HLNE":666,"ARES":667,"FRSH":668,"FDS":669,"EL":670,"JKHY":671,"MOS":672,"CTSH":673,"LULU":674,"MOH":675,"PINS":676,"MKC":677,"BBWI":678,"APTV":679,"ENPH":680,"G":681,"HRL":682,"CHE":683,"JOBY":684,"FIS":685,"DT":686,"GEN":687,"NVO":688,"CAG":689,"PTC":690,"ABT":691,"OLLI":692,"OKTA":693,"ELF":694,"KMX":695,"PATH":696,"EPAM":697,"CRM":698,"GIS":699,"PAYX":700,"ADBE":701,"FBIN":702,"ARE":703,"PLNT":704,"CPRT":705,"BRO":706,"GWRE":707,"ADP":708,"MANH":709,"FND":710,"CELH":711,"NKE":712,"ACN":713,"BR":714,"CPB":715,"PODD":716,"AVAV":717,"BLDR":718,"PAYC":719,"NTNX":720,"CHKP":721,"DOCU":722,"BSX":723,"FICO":724,"FOUR":725,"GDDY":726,"AVTR":727,"INTU":728,"PCTY":729,"ACHR":730,"DKNG":731,"AXON":732,"FISV":733,"NOW":734,"BMI":735,"ESTC":736,"OWL":737,"BULL":738,"IT":739,"CSGP":740,"GTLB":741,"HUBS":742,"DOCS":743,"FLUT":744,"LCID":745,"KLAR":746,"DUOL":747},"w":{"AXTI":13,"LITE":597,"HYMC":40,"AAOI":268,"BE":17,"AEHR":36,"PL":114,"CIEN":461,"CAR":1,"LASR":203,"FSLY":239,"COHR":94,"FORM":116,"MU":183,"AMPX":180,"APLD":29,"NBIS":181,"CIFR":46,"SATS":388,"IREN":20,"HUT":80,"POWL":345,"FIX":385,"AGX":624,"GLW":697,"NVTS":12,"AMKR":59,"AEIS":627,"MKSI":383,"CENX":727,"GSAT":159,"CLS":88,"DOCN":81,"INTC":147,"PARR":738,"LRCX":513,"MOD":539,"LGN":50,"LUNR":48,"ALB":76,"FN":352,"ONTO":85,"MTZ":432,"HBM":242,"ATI":508,"IRDM":21,"FTI":706,"KEYS":411,"MRVL":176,"GEV":532,"ECG":629,"FIVE":177,"FRO":185,"LSCC":131,"MTSI":215,"NOK":168,"MPWR":179,"CRDO":6,"AMAT":608,"BTSG":349,"MYRG":396,"AA":744,"AU":591,"CAT":565,"CRS":453,"KLAC":413,"DELL":124,"MT":457,"MRNA":286,"IESC":542,"LFUS":498,"NVT":410,"AMD":77,"ON":24,"ACLS":207,"ESE":518,"DAVE":5,"CGNX":370,"JBL":212,"ACHC":361,"ESI":372,"FLEX":234,"FDX":315,"ENTG":194,"FCX":373,"ALAB":49,"CMI":493,"ADI":256,"PLUG":514,"DBD":324,"CRUS":316,"JBHT":192,"CORZ":182,"ARW":122,"ANET":109,"AVT":134,"GFS":99,"EQX":394,"ASML":633,"C":246,"ONDS":154,"DHT":310,"KGC":398,"CCJ":367,"PLXS":568,"AVGO":158,"PAAS":445,"LUMN":64,"MRX":409,"EQIX":278,"NUE":295,"DNN":169,"DY":503,"GOOGL":204,"AGI":494,"CW":519,"CRWV":69,"APH":214,"DAR":714,"GOOG":209,"BWXT":430,"ATMU":579,"MSGS":510,"MAR":229,"ODFL":338,"ARM":98,"KNX":350,"ITT":538,"FTAI":415,"FLS":610,"FCFS":440,"EME":566,"HWM":530,"HTZ":41,"PR":720,"LMND":10,"IBKR":68,"HST":317,"AG":342,"GFI":525,"NEM":691,"AEM":559,"DD":580,"JCI":630,"NPO":522,"APG":294,"PVH":374,"BK":263,"IAG":693,"MEOH":741,"HAL":631,"CHRW":108,"GNRC":446,"CASY":463,"NTRS":335,"CDE":557,"BWA":468,"ALSN":587,"HL":572,"IDCC":267,"FNV":576,"KEX":527,"HLT":285,"IRM":193,"CE":650,"HAS":264,"BPOP":515,"CFG":570,"HPE":248,"DLR":199,"EBAY":153,"PLD":272,"BP":696,"MUR":711,"HXL":251,"GMED":291,"AAP":292,"MCHP":137,"RELY":38,"CAVA":106,"DOW":739,"JBLU":18,"AZN":575,"ETR":620,"CSX":439,"ASTS":742,"MRK":656,"CSCO":314,"MS":245,"COKE":722,"PH":569,"CLH":602,"GRMN":359,"BURL":363,"AME":562,"EVR":213,"NVDA":227,"B":604,"GM":240,"GLNG":677,"HUBB":590,"PCAR":616,"GKOS":223,"BNL":465,"ILMN":112,"EXPE":52,"FUTU":149,"FLY":53,"IONS":555,"BKR":710,"IBP":357,"DAL":273,"CROX":254,"EXK":187,"BEN":156,"GS":482,"CBOE":520,"ARMK":280,"BALL":392,"NDSN":451,"ETN":549,"BKH":414,"FRT":408,"KIM":343,"NOV":658,"AEO":259,"KEY":505,"CTRE":600,"MDLN":340,"RIVN":104,"GH":65,"M":386,"AMG":404,"MLI":550,"JLL":167,"AEP":657,"FERG":509,"APA":733,"EIX":723,"CAH":614,"ARGX":252,"ALLY":142,"BMY":434,"NRG":464,"DOV":543,"H":113,"LBRT":709,"AHR":554,"EWBC":469,"FTV":381,"NI":564,"HII":585,"GAP":426,"LVS":198,"CTVA":701,"NET":26,"OHI":462,"PFG":322,"NLY":418,"AMZN":303,"PNC":447,"MEDP":281,"LUV":195,"NEE":665,"GWW":618,"MTCH":97,"PBF":737,"LHX":622,"DE":669,"FITB":474,"FNB":517,"PFE":454,"ASO":365,"PNW":571,"MGM":401,"CRGY":731,"IVZ":296,"ALGN":150,"EVRG":641,"COLB":459,"ALHC":395,"IEX":452,"LNT":598,"AIT":556,"AEE":609,"DINO":605,"MP":128,"CVNA":63,"MUSA":599,"NYT":560,"AGNC":358,"MTB":603,"CB":545,"O":472,"CFR":561,"ALL":448,"NXT":717,"OVV":719,"CHRD":735,"LCII":667,"FHN":537,"NSC":478,"LOGI":118,"AAPL":377,"BAC":437,"HSIC":329,"HIG":488,"PPL":645,"CRSP":82,"GILD":623,"AMGN":528,"FE":675,"ATO":659,"CNP":621,"APD":668,"DVN":732,"BG":692,"CF":728,"MTDR":729,"HON":606,"EPRT":421,"CINF":393,"ADC":502,"ABNB":151,"FLR":636,"ORA":655,"OKLO":7,"AGCO":663,"DKS":279,"MPC":698,"OSK":674,"LEU":175,"AS":289,"CRL":325,"JPM":583,"FFIV":217,"PSA":320,"OXY":730,"LYB":743,"FANG":702,"HCA":642,"LECO":481,"GE":638,"EXPD":420,"DX":406,"CCL":341,"EMR":495,"IONQ":2,"EG":235,"COP":713,"NTRA":191,"LIN":664,"DTE":652,"IFF":330,"CTRA":734,"MNST":521,"BIDU":58,"CPA":290,"BMNR":196,"DECK":347,"ONB":483,"CACC":79,"ETSY":42,"F":255,"APP":22,"CMS":661,"FOXA":232,"ACGL":500,"CZR":526,"CHH":244,"JNJ":651,"CVX":670,"PII":311,"OMF":266,"ITW":558,"CRCL":27,"AFL":399,"GLPI":466,"HOG":416,"DTM":625,"CRH":615,"CCK":581,"LYV":671,"AAON":547,"KRMN":523,"EPD":653,"PCG":726,"PEP":574,"RS":535,"EMN":607,"META":160,"PPG":360,"CR":460,"CPAY":127,"EOG":712,"MO":707,"PHM":301,"ANF":700,"CVS":672,"COST":584,"NTR":703,"ADM":694,"KO":666,"GME":274,"BIO":225,"BIIB":442,"INSM":724,"DVA":640,"DG":157,"D":678,"ELS":475,"AN":379,"OMC":297,"KMI":660,"LNG":715,"ET":649,"FRPT":218,"NU":441,"CUBE":455,"JD":162,"MSI":487,"PSTG":143,"QRVO":436,"HOOD":9,"CARR":684,"MET":277,"OKE":683,"ES":626,"BA":435,"AFRM":8,"MC":222,"DOC":344,"OSCR":161,"AUR":15,"LH":378,"HBAN":422,"FCNCA":479,"EXR":326,"AKAM":309,"LMT":689,"CNX":644,"HESM":704,"DHI":308,"AXP":271,"LAZ":306,"EAT":485,"FAST":725,"MLM":643,"IR":567,"MTD":531,"AIG":456,"CART":283,"AR":685,"BOOT":302,"CHD":507,"PB":496,"NTAP":170,"CLSK":33,"NOC":634,"MPLX":601,"EQT":595,"GGG":611,"CBRE":216,"CDNS":47,"MCK":586,"LLY":637,"LOW":417,"EQR":443,"CSL":391,"PFGC":307,"MAS":275,"MSCI":260,"CVCO":351,"BTDR":30,"DUK":679,"ED":682,"PKG":402,"BDX":424,"ECL":563,"CMCSA":257,"NDAQ":236,"FWONK":486,"DGX":492,"CME":676,"DDOG":28,"MCD":490,"PEG":654,"EHC":619,"ESS":484,"EXC":686,"IDXX":327,"BLD":364,"NXPI":276,"HMY":89,"CCI":425,"COR":473,"MKL":407,"BABA":120,"NWSA":247,"CI":429,"NXST":163,"MIDD":552,"AAL":87,"DIS":224,"PNFP":313,"ORLY":553,"INVH":371,"PSKY":125,"ABBV":536,"DRI":339,"BLK":293,"PDD":333,"NFLX":716,"AMT":428,"MDB":51,"MMM":423,"HQY":130,"CDW":230,"BBY":288,"COF":226,"PLTR":70,"CG":111,"KVUE":511,"OC":210,"BKNG":121,"CHTR":184,"BTU":740,"GEHC":480,"AYI":298,"CPT":516,"A":262,"MTN":353,"LYFT":86,"EW":366,"KR":578,"NCLH":300,"CEG":403,"ICE":573,"MA":337,"FTNT":231,"GD":577,"FROG":477,"PG":529,"CRWD":100,"ORCL":16,"KTOS":540,"CL":497,"AVY":551,"AZO":354,"NEU":544,"AVB":449,"BAM":144,"AON":253,"IQV":284,"CNR":718,"AMCR":489,"NTES":318,"AMH":412,"FIGR":205,"CPNG":166,"JHX":397,"GLXY":35,"HD":389,"MARA":23,"FNF":321,"MAA":444,"IBM":145,"PEGA":119,"BIRK":368,"HPQ":172,"DLTR":241,"AWK":699,"ALNY":695,"MHK":299,"MSFT":75,"MCO":237,"ALK":66,"CLF":141,"J":312,"COMP":74,"CHDN":287,"BROS":705,"BRZE":34,"HSY":708,"FSLR":721,"CNH":736,"MDLZ":681,"ISRG":356,"NVR":380,"LAD":384,"PANW":201,"HEI":548,"CNC":458,"GPN":123,"LW":249,"APO":32,"LPLA":506,"PYPL":93,"ALLE":596,"DHR":431,"PGR":346,"AMP":467,"ELV":382,"HLI":219,"BX":91,"COIN":19,"AOS":648,"GPC":269,"QCOM":243,"KRC":110,"MRSH":336,"KKR":78,"HUM":228,"CACI":639,"PM":647,"MDT":632,"PNR":524,"ESAB":202,"LII":690,"BXP":155,"JEF":305,"IOT":39,"BAH":334,"BRK-B":628,"ADSK":117,"EQH":107,"MELI":331,"EFX":133,"KDP":592,"CTAS":450,"DBX":138,"CNM":635,"KMB":504,"DASH":25,"INFY":174,"CHWY":164,"MSTR":11,"BJ":613,"EXP":541,"AJG":375,"MORN":152,"EXE":687,"COO":646,"ACI":688,"OTIS":491,"DPZ":501,"IP":499,"CMG":304,"BAX":165,"EXLS":173,"LDOS":512,"POOL":265,"QUBT":4,"CVLT":258,"DXCM":589,"KHC":673,"BILL":102,"ACM":387,"EOSE":14,"CLX":612,"KNSL":390,"ONON":135,"LEN":348,"PCOR":43,"BSY":95,"HLNE":61,"ARES":45,"FRSH":84,"FDS":140,"EL":319,"JKHY":328,"MOS":617,"CTSH":270,"LULU":476,"MOH":470,"PINS":71,"MKC":533,"BBWI":220,"APTV":588,"ENPH":355,"G":188,"HRL":419,"CHE":594,"JOBY":126,"FIS":101,"DT":139,"GEN":90,"NVO":189,"CAG":662,"PTC":323,"ABT":680,"OLLI":282,"OKTA":67,"ELF":438,"KMX":745,"PATH":115,"EPAM":221,"CRM":129,"GIS":593,"PAYX":211,"ADBE":178,"FBIN":582,"ARE":72,"PLNT":405,"CPRT":471,"BRO":362,"GWRE":37,"ADP":250,"MANH":148,"FND":332,"CELH":534,"NKE":190,"ACN":136,"BR":200,"CPB":427,"PODD":400,"AVAV":238,"BLDR":376,"PAYC":103,"NTNX":56,"CHKP":546,"DOCU":233,"BSX":369,"FICO":57,"FOUR":92,"GDDY":186,"AVTR":197,"INTU":96,"PCTY":261,"ACHR":83,"DKNG":433,"AXON":55,"FISV":73,"NOW":54,"BMI":747,"ESTC":146,"OWL":31,"BULL":3,"IT":206,"CSGP":171,"GTLB":132,"HUBS":60,"DOCS":44,"FLUT":208,"LCID":746,"KLAR":62,"DUOL":105}}]}