{"weeks":[{"wk":"2026-W11","date":"2026-03-15","d":{"MSOS":1,"NURS":2,"FCG":3,"GBTC":4,"XLU":5,"WGMI":6,"XOP":7,"IYZ":8,"BLOK":9,"XES":10,"XLE":11,"AMLP":12,"ESPO":13,"AGENT":14,"ICLN":15,"CIBR":16,"ARKF":17,"UFO":18,"OPTIC":19,"OIH":20,"ARKK":21,"DRNZ":22,"LIT":23,"QNTM":24,"HYDR":25,"CHEMS":26,"LIDAR":27,"WCLD":28,"XBI":29,"FAN":30,"IGV":31,"AIPO":32,"MOO":33,"CHEMG":34,"URA":35,"TAN":36,"XME":37,"QQQE":38,"REMX":39,"PBJ":40,"IYR":41,"BJK":42,"IPAY":43,"SMH":44,"KIE":45,"IBUY":46,"ITA":47,"SILJ":48,"XLP":49,"EEM":50,"IWO":51,"COOL":52,"SIL":53,"ARKG":54,"BOAT":55,"GDX":56,"FXI":57,"XLY":58,"FFTY":59,"GDXJ":60,"PEJ":61,"XHS":62,"EWZ":63,"COPX":64,"XLF":65,"KBE":66,"KRE":67,"DRIV":68,"KCE":69,"XPH":70,"XLV":71,"XLB":72,"XLI":73,"XRT":74,"JETS":75,"ROBO":76,"ITB":77,"PAVE":78,"PHO":79,"IYT":80,"XHE":81,"SLX":82,"WOOD":83},"w":{"MSOS":29,"NURS":20,"FCG":9,"GBTC":57,"XLU":18,"WGMI":3,"XOP":8,"IYZ":21,"BLOK":35,"XES":14,"XLE":12,"AMLP":24,"ESPO":68,"AGENT":67,"ICLN":4,"CIBR":60,"ARKF":61,"UFO":19,"OPTIC":1,"OIH":23,"ARKK":55,"DRNZ":17,"LIT":11,"QNTM":28,"HYDR":7,"CHEMS":15,"LIDAR":6,"WCLD":70,"XBI":26,"FAN":22,"IGV":69,"AIPO":10,"MOO":13,"CHEMG":2,"URA":16,"TAN":5,"XME":31,"QQQE":38,"REMX":27,"PBJ":36,"IYR":25,"BJK":59,"IPAY":72,"SMH":30,"KIE":65,"IBUY":74,"ITA":34,"SILJ":50,"XLP":37,"EEM":41,"IWO":43,"COOL":32,"SIL":49,"ARKG":48,"BOAT":39,"GDX":40,"FXI":76,"XLY":73,"FFTY":33,"GDXJ":51,"PEJ":77,"XHS":52,"EWZ":45,"COPX":47,"XLF":81,"KBE":53,"KRE":46,"DRIV":58,"KCE":79,"XPH":63,"XLV":44,"XLB":42,"XLI":56,"XRT":78,"JETS":83,"ROBO":54,"ITB":75,"PAVE":62,"PHO":80,"IYT":66,"XHE":82,"SLX":64,"WOOD":71}},{"wk":"2026-W12","date":"2026-03-16","d":{"GBTC":1,"AIPO":2,"FAN":3,"WGMI":4,"OPTIC":5,"BLOK":6,"TAN":7,"ARKK":8,"ARKF":9,"UFO":10,"ESPO":11,"ICLN":12,"IYZ":13,"XLU":14,"FCG":15,"QNTM":16,"XBI":17,"LIT":18,"HYDR":19,"QQQE":20,"CHEMS":21,"MSOS":22,"DRNZ":23,"XLE":24,"XOP":25,"XES":26,"CHEMG":27,"LIDAR":28,"URA":29,"AGENT":30,"MOO":31,"AMLP":32,"CIBR":33,"NURS":34,"IGV":35,"WCLD":36,"IYR":37,"PBJ":38,"SMH":39,"IPAY":40,"XME":41,"REMX":42,"EEM":43,"IWO":44,"KIE":45,"OIH":46,"ITA":47,"IBUY":48,"BOAT":49,"FXI":50,"BJK":51,"SILJ":52,"FFTY":53,"DRIV":54,"COOL":55,"XLP":56,"EWZ":57,"GDXJ":58,"SIL":59,"XHS":60,"GDX":61,"ARKG":62,"XLV":63,"XLF":64,"XPH":65,"KBE":66,"KRE":67,"KCE":68,"XLB":69,"ROBO":70,"XLI":71,"XLY":72,"COPX":73,"PEJ":74,"IYT":75,"PHO":76,"ITB":77,"XHE":78,"JETS":79,"SLX":80,"PAVE":81,"XRT":82,"WOOD":83},"w":{"GBTC":57,"AIPO":18,"FAN":20,"WGMI":2,"OPTIC":1,"BLOK":35,"TAN":3,"ARKK":56,"ARKF":61,"UFO":16,"ESPO":68,"ICLN":7,"IYZ":12,"XLU":17,"FCG":10,"QNTM":28,"XBI":26,"LIT":19,"HYDR":11,"QQQE":38,"CHEMS":14,"MSOS":15,"DRNZ":8,"XLE":9,"XOP":6,"XES":22,"CHEMG":4,"LIDAR":5,"URA":24,"AGENT":67,"MOO":13,"AMLP":21,"CIBR":63,"NURS":27,"IGV":69,"WCLD":70,"IYR":23,"PBJ":36,"SMH":30,"IPAY":72,"XME":31,"REMX":29,"EEM":41,"IWO":44,"KIE":59,"OIH":25,"ITA":33,"IBUY":74,"BOAT":39,"FXI":76,"BJK":60,"SILJ":49,"FFTY":34,"DRIV":58,"COOL":32,"XLP":37,"EWZ":45,"GDXJ":51,"SIL":48,"XHS":55,"GDX":40,"ARKG":50,"XLV":46,"XLF":80,"XPH":62,"KBE":52,"KRE":43,"KCE":78,"XLB":42,"ROBO":53,"XLI":54,"XLY":73,"COPX":47,"PEJ":77,"IYT":66,"PHO":81,"ITB":75,"XHE":82,"JETS":83,"SLX":65,"PAVE":64,"XRT":79,"WOOD":71}}]}